{
  "type": "forge:conditional",
  "recipes": [
    {
      "conditions": [
        {
          "type": "assortedtech:part_enabled",
          "part": "torches"
        }
      ],
      "recipe": {
        "type": "minecraft:crafting_shaped",
        "key": {
          "P": {
            "tag": "forge:dusts/glowstone"
          },
          "R": {
            "tag": "forge:dusts/redstone"
          },
          "X": {
            "tag": "forge:rods/wooden"
          }
        },
        "pattern": [
          "P",
          "X",
          "R"
        ],
        "result": {
          "item": "assortedtech:glowstone_torch"
        }
      }
    }
  ]
}